gremlinapi/__init__.py
gremlinapi/alfi.py
gremlinapi/apikeys.py
gremlinapi/attack_helpers.py
gremlinapi/attacks.py
gremlinapi/cli.py
gremlinapi/clients.py
gremlinapi/companies.py
gremlinapi/config.py
gremlinapi/containers.py
gremlinapi/contracts.py
gremlinapi/exceptions.py
gremlinapi/executions.py
gremlinapi/gremlinapi.py
gremlinapi/halts.py
gremlinapi/http_clients.py
gremlinapi/kubernetes.py
gremlinapi/kubernetes_attack_helpers.py
gremlinapi/metadata.py
gremlinapi/metrics.py
gremlinapi/oauth.py
gremlinapi/orgs.py
gremlinapi/providers.py
gremlinapi/reliability_tests.py
gremlinapi/reports.py
gremlinapi/saml.py
gremlinapi/scenario_graph_helpers.py
gremlinapi/scenario_helpers.py
gremlinapi/scenarios.py
gremlinapi/schedules.py
gremlinapi/templates.py
gremlinapi/users.py
gremlinapi/util.py
tests/__init__.py
tests/pytest_orgs.py
tests/pytest_reliability_tests.py
tests/test_alfi.py
tests/test_all.py
tests/test_apikeys.py
tests/test_attack_helpers.py
tests/test_attacks.py
tests/test_base.py
tests/test_cli.py
tests/test_clients.py
tests/test_companies.py
tests/test_containers.py
tests/test_contracts.py
tests/test_executions.py
tests/test_gremlinapi.py
tests/test_halts.py
tests/test_httpclient.py
tests/test_kubernetes.py
tests/test_metadata.py
tests/test_metrics.py
tests/test_oauth.py
tests/test_orgs.py
tests/test_providers.py
tests/test_reports.py
tests/test_saml.py
tests/test_scenario_graph_helpers.py
tests/test_scenario_helpers.py
tests/test_scenarios.py
tests/test_schedules.py
tests/test_templates.py
tests/test_users.py
tests/util.py
gremlinapi-0.18.3.dist-info/LICENSE
gremlinapi-0.18.3.dist-info/METADATA
gremlinapi-0.18.3.dist-info/WHEEL
gremlinapi-0.18.3.dist-info/entry_points.txt
gremlinapi-0.18.3.dist-info/top_level.txt
gremlinapi-0.18.3.dist-info/RECORD
