Metadata-Version: 2.1
Name: gremlinapi
Version: 0.18.3
Summary: Gremlin library for Python
Home-page: https://github.com/gremlin/gremlin-python/
Author: Kyle Hultman
Author-email: kyle@gremlin.com
License: Apache 2.0
Classifier: Programming Language :: Python :: 3.7
Classifier: Programming Language :: Python :: 3.8
Requires-Python: >=3.7
License-File: LICENSE
Requires-Dist: requests >=2.22.0
Requires-Dist: urllib3 >=1.25.8
